multiinfo/__init__.py
multiinfo/base.py
multiinfo/cli.py
multiinfo/core.py
multiinfo/endpoints.py
multiinfo/exceptions.py
multiinfo/factories.py
multiinfo/settings.py
multiinfo-0.4.0.dist-info/METADATA
multiinfo-0.4.0.dist-info/RECORD
multiinfo-0.4.0.dist-info/WHEEL
multiinfo-0.4.0.dist-info/entry_points.txt
multiinfo-0.4.0.dist-info/top_level.txt
