Metadata-Version: 2.1
Name: multiinfo
Version: 0.4.0
Summary: Python wrapper for Polkomtel's MultiInfo SMS service
Home-page: https://github.com/wooyek/multiinfo
Author: Janusz Skonieczny
Author-email: js+pypi@bravelabs.pl
License: GNU General Public License v3
Keywords: multiinfo
Platform: UNKNOWN
Classifier: Development Status :: 2 - Pre-Alpha
Classifier: Intended Audience :: Developers
Classifier: License :: OSI Approved :: GNU General Public License v3 (GPLv3)
Classifier: Natural Language :: English
Classifier: Programming Language :: Python :: 2
Classifier: Programming Language :: Python :: 2.7
Classifier: Programming Language :: Python :: 3
Classifier: Programming Language :: Python :: 3.4
Classifier: Programming Language :: Python :: 3.5
Classifier: Programming Language :: Python :: 3.6
Classifier: Programming Language :: Python :: 3.7
Requires-Python: >=2.7
Provides-Extra: factories
Requires-Dist: six
Requires-Dist: click
Requires-Dist: click-log
Requires-Dist: envparse
Requires-Dist: dynaconf (==0.5.4)
Requires-Dist: python-box
Requires-Dist: pyyaml
Requires-Dist: requests
Requires-Dist: pathlib; python_version < "3.3"
Requires-Dist: pathlib2; python_version < "3.3"
Requires-Dist: enum34; python_version < "3.4"
Provides-Extra: factories
Requires-Dist: factory-boy; extra == 'factories'
